crop/__init__.py
crop/interactivecrop.py
crop/samples.py
crop/shapes.py
crop/widgets_helper.py
interactivecrop/__init__.py
interactivecrop/interactivecrop.py
interactivecrop/samples.py
interactivecrop/shapes.py
interactivecrop/widgets_helper.py
interactivecrop/image_samples/.DS_Store
interactivecrop/image_samples/bird.jpg
interactivecrop/image_samples/castle.jpg
interactivecrop/image_samples/rhino.jpg
interactivecrop/image_samples/statue.jpg
interactivecrop/image_samples/tower.jpg
interactivecrop-0.0.10.dist-info/LICENSE.txt
interactivecrop-0.0.10.dist-info/METADATA
interactivecrop-0.0.10.dist-info/WHEEL
interactivecrop-0.0.10.dist-info/top_level.txt
interactivecrop-0.0.10.dist-info/RECORD
