Metadata-Version: 2.1
Name: interactivecrop
Version: 0.0.10
Summary: An interactive image cropping tool for Jupyter Notebooks in Python
Home-page: https://github.com/samjett247/interactive_crop
Author: Sam Jett
Author-email: samjett247@gmail.com
License: UNKNOWN
Platform: UNKNOWN
Classifier: Programming Language :: Python :: 3
Classifier: License :: OSI Approved :: GNU General Public License v3 or later (GPLv3+)
Classifier: Operating System :: OS Independent
Requires-Dist: pandas
Requires-Dist: numpy
Requires-Dist: pillow
Requires-Dist: ipywidgets
Requires-Dist: ipython
